jbtuner_manager/__init__.py
jbtuner_manager/__main__.py
jbtuner_manager/main.py
jbtuner_manager-0.1.1.dist-info/entry_points.txt
jbtuner_manager-0.1.1.dist-info/WHEEL
jbtuner_manager-0.1.1.dist-info/METADATA
jbtuner_manager-0.1.1.dist-info/RECORD
