Metadata-Version: 2.1
Name: jbtuner-manager
Version: 0.1.1
Summary: 
Author: Ying Shaodong
Author-email: gavin.ying@chordx.co
Requires-Python: >3.7,<4.0
Classifier: Programming Language :: Python :: 3
Classifier: Programming Language :: Python :: 3.8
Classifier: Programming Language :: Python :: 3.9
Requires-Dist: adafruit-ampy (>=1.1.0,<2.0.0)
Requires-Dist: typer[all] (>=0.3.2,<0.4.0)
